vhh_sbd/Configuration.py
vhh_sbd/DeepSBD.py
vhh_sbd/Evaluation.py
vhh_sbd/Model.py
vhh_sbd/PreProcessing.py
vhh_sbd/SBD.py
vhh_sbd/Shot.py
vhh_sbd/Video.py
vhh_sbd/__init__.py
vhh_sbd/utils.py
vhh_sbd-1.2.1.dist-info/LICENSE
vhh_sbd-1.2.1.dist-info/METADATA
vhh_sbd-1.2.1.dist-info/WHEEL
vhh_sbd-1.2.1.dist-info/top_level.txt
vhh_sbd-1.2.1.dist-info/RECORD
