Metadata-Version: 2.1
Name: vhh-sbd
Version: 1.2.1
Summary: Shot Boundary Detection Package
Home-page: https://github.com/dahe-cvl/vhh_sbd
Author: Daniel Helm
Author-email: daniel.helm@tuwien.ac.at
License: UNKNOWN
Platform: UNKNOWN
Requires-Dist: Pillow
Requires-Dist: PyYAML
Requires-Dist: Sphinx
Requires-Dist: matplotlib
Requires-Dist: numpy
Requires-Dist: opencv-python
Requires-Dist: scipy
Requires-Dist: sphinxcontrib-autoyaml
Requires-Dist: sphinxcontrib-bibtex
